MANIFEST.in
README.rst
setup.cfg
setup.py
tinyschema/__init__.py
tinyschema/compat.py
tinyschema/construct.py
tinyschema/datavalidation.py
tinyschema/inspection.py
tinyschema/langhelpers.py
tinyschema/parser.py
tinyschema.egg-info/PKG-INFO
tinyschema.egg-info/SOURCES.txt
tinyschema.egg-info/dependency_links.txt
tinyschema.egg-info/entry_points.txt
tinyschema.egg-info/not-zip-safe
tinyschema.egg-info/requires.txt
tinyschema.egg-info/top_level.txt
tinyschema/locales/ja/LC_MESSAGES/tinyschema.mo
tinyschema/locales/ja/LC_MESSAGES/tinyschema.po
tinyschema/renderer/__init__.py
tinyschema/tests/__init__.py
tinyschema/tests/schemas.py
tinyschema/tests/test_inspect.py
tinyschema/tests/test_inspection.py
tinyschema/tests/test_it.py
tinyschema/tests/test_parser.py
tinyschema/tests/test_schema.py
tinyschema/tests/test_translation.py