Metadata-Version: 1.1
Name: tinyschema
Version: 0.2.1
Summary: tiny schema implementation
Home-page: https://github.com/podhmo/tinyschema
Author: UNKNOWN
Author-email: UNKNOWN
License: UNKNOWN
Platform: UNKNOWN
Classifier: Programming Language :: Python
Classifier: Programming Language :: Python :: Implementation :: CPython
